cqlalchemy/__init__.py
cqlalchemy/scaffold/__init__.py
cqlalchemy/scaffold/build.py
cqlalchemy/scaffold/extension.py
cqlalchemy/scaffold/templates/__init__.py
cqlalchemy/scaffold/templates/common.docs.template
cqlalchemy/scaffold/templates/common.template
cqlalchemy/scaffold/templates/enum.custom.method.template
cqlalchemy/scaffold/templates/enum.query.attr.template
cqlalchemy/scaffold/templates/enum.template
cqlalchemy/scaffold/templates/extension.template
cqlalchemy/scaffold/templates/number.query.attr.template
cqlalchemy/scaffold/templates/pyproject.toml.template
cqlalchemy/scaffold/templates/query.template
cqlalchemy/scripts/__ini__.py
cqlalchemy/scripts/generate.py
cqlalchemy/scripts/main.py
cqlalchemy/stac/__init__.py
cqlalchemy/stac/query.py
cqlalchemy-0.1.0.dist-info/AUTHORS.md
cqlalchemy-0.1.0.dist-info/LICENSE.txt
cqlalchemy-0.1.0.dist-info/METADATA
cqlalchemy-0.1.0.dist-info/WHEEL
cqlalchemy-0.1.0.dist-info/entry_points.txt
cqlalchemy-0.1.0.dist-info/RECORD
