Metadata-Version: 2.1
Name: cqlalchemy
Version: 0.1.0
Summary: library for constructing cql2-json queries and for generating libraries with multiple STAC extensions"
License: MIT
Author: David Raleigh
Author-email: davidraleigh@gmail.com
Requires-Python: >=3.9,<4.0
Classifier: License :: OSI Approved :: MIT License
Classifier: Programming Language :: Python :: 3
Classifier: Programming Language :: Python :: 3.9
Classifier: Programming Language :: Python :: 3.10
Classifier: Programming Language :: Python :: 3.11
Classifier: Programming Language :: Python :: 3.12
Classifier: Programming Language :: Python :: 3.13
Provides-Extra: scaffold
Requires-Dist: click (>=8.1.7,<9.0.0)
Requires-Dist: requests (>=2.32.3,<3.0.0)
Requires-Dist: shapely (>=2.0.6,<3.0.0)
